pape_docs/__init__.py
pape_docs/helpers/__init__.py
pape_docs/helpers/dir_write_tester.py
pape_docs/helpers/docs_dir_guard.py
pape_docs/helpers/file_name_part_retriever.py
pape_docs/helpers/pape_docs_dir_finder.py
pape_docs/helpers/template_loader.py
pape_docs/templates/doc.md
pape_docs-0.5.0.dist-info/METADATA
pape_docs-0.5.0.dist-info/WHEEL
pape_docs-0.5.0.dist-info/entry_points.txt
pape_docs-0.5.0.dist-info/licenses/LICENSE
pape_docs-0.5.0.dist-info/RECORD
