Metadata-Version: 2.4
Name: pape_docs
Version: 0.5.0
Summary: A tool for flexibly managing templated docs of all kinds.
Author-email: Carter Pape <pape-docs-author@carterpape.com>
License-File: LICENSE
Requires-Python: >=3.13
Requires-Dist: click>=8.2.1
Requires-Dist: pape>=0.1.0
Requires-Dist: pathvalidate>=3.3.1
Requires-Dist: python-dotenv>=1.1.1
